[
  {
    "theme": "Sportifs",
    "name": "Bonjour",
    "id": 1582018073558
  },
  {
    "theme": "Santé",
    "name": "Docteurs",
    "id": 1583739103866,
    "imageId": "1585592306399"
  },
  {
    "name": "Pas de nom de quiz",
    "theme": "Autres",
    "creationDate": "2020-03-17T14:20:28.518Z",
    "id": 1584454842993
  },
  {
    "name": "NewQuiz!!",
    "theme": "Actor",
    "creationDate": "2020-03-23T12:39:22.944Z",
    "id": 1584967171131
  },
  {
    "name": "Legumes",
    "theme": "Autres",
    "creationDate": "2020-03-23T21:07:33.174Z",
    "id": 1584997706362
  },
  {
    "name": "Ok",
    "theme": "Actor",
    "creationDate": "2020-03-30T16:50:24.815Z",
    "id": 1585587024841
  },
  {
    "name": "Pirate!",
    "theme": "Android",
    "creationDate": "2020-03-30T16:52:00.061Z",
    "imageId": "1585587120086",
    "id": 1585587120246
  },
  {
    "name": "Pirate2",
    "theme": "Android",
    "creationDate": "2020-03-30T17:15:01.681Z",
    "imageId": "1585588501713",
    "id": 1585588501884
  },
  {
    "name": "another test",
    "theme": "Sport",
    "creationDate": "2020-03-30T17:23:23.895Z",
    "id": 1585589003914
  },
  {
    "name": "ok?",
    "theme": "Android",
    "creationDate": "2020-03-30T17:23:36.294Z",
    "imageId": "1585589016314",
    "id": 1585589016403
  }
]